anx_interface/__init__.py
anx_interface/anx_interface.py
anx_interface/assets/__init__.py
anx_interface/assets/device_camera.py
anx_interface/assets/device_gnss.py
anx_interface/assets/device_imu.py
anx_interface/tests/__init__.py
anx_interface/tests/test_device_camera.py
anx_interface/tests/test_listen_device_camera.py
anx_interface/tflite_interface.py
anx_interface/tools/__init__.py
anx_interface/tools/anx.py
anx_interface/utils/__init__.py
anx_interface/utils/fifo.py
anx_logging/__init__.py
anx_logging/perf_logger.py
anx_mock/__init__.py
anx_mock/anx_mock.py
anx_mock/assets/__init__.py
anx_mock/assets/device_camera.py
anx_mock/assets/device_gnss.py
anx_mock/assets/device_imu.py
anx_mock/utils.py
anx_proto/.DS_Store
anx_proto/__init__.py
anx_proto/python/__init__.py
anx_proto/python/assets_pb2.py
anx_proto/python/common_pb2.py
anx_proto/python/device_pb2.py
anx_proto/python/model_pb2.py
anx_interface-0.5.3.dist-info/METADATA
anx_interface-0.5.3.dist-info/WHEEL
anx_interface-0.5.3.dist-info/entry_points.txt
anx_interface-0.5.3.dist-info/RECORD
